obfuscated/__init__.py
obfuscated/asgi.py
obfuscated/settings.py
obfuscated/urls.py
obfuscated/views.py
obfuscated/wsgi.py
url_obfuscated/__init__.py
url_obfuscated/apps.py
url_obfuscated/decorators.py
url_obfuscated/helpers.py
url_obfuscated/migrations/__init__.py
url_obfuscated/templatetags/__init__.py
url_obfuscated/templatetags/obfuscate_tags.py
url_obfuscated-1.0.0.dist-info/LICENSE
url_obfuscated-1.0.0.dist-info/METADATA
url_obfuscated-1.0.0.dist-info/WHEEL
url_obfuscated-1.0.0.dist-info/top_level.txt
url_obfuscated-1.0.0.dist-info/RECORD
