Metadata-Version: 2.1
Name: url-obfuscated
Version: 1.0.0
Summary: Easy and Simple method to obfuscate and deobfuscate your Django URLs.
Home-page: https://github.com/dhyanipalan/url_obfuscated
Download-URL: https://github.com/dhyanipalan/url_obfuscated
Author: Dhyanikumar Palan
Author-email: dhyanipalan@gmail.com
Maintainer: Dhyanikumar Palan
Maintainer-email: dhyanipalan@gmail.com
License: Apache License
Keywords: django,Python,urlobfuscate,encrypt
Classifier: License :: OSI Approved :: Academic Free License (AFL)
Classifier: Natural Language :: English
Classifier: Programming Language :: Python
Classifier: Programming Language :: Python :: 3
Classifier: Operating System :: Unix
Classifier: Operating System :: MacOS :: MacOS X
Classifier: Operating System :: Microsoft :: Windows
Classifier: Framework :: Django
License-File: LICENSE
Requires-Dist: Django >=2.2
Requires-Dist: pycryptodome ==3.20.0
